cvm_dify/__init__.py
cvm_dify-0.1.2.dist-info/METADATA
cvm_dify-0.1.2.dist-info/WHEEL
cvm_dify-0.1.2.dist-info/entry_points.txt
cvm_dify-0.1.2.dist-info/RECORD
