Metadata-Version: 2.4
Name: cvm-dify
Version: 0.1.2
Summary: CVM Dify MCP Server 
Requires-Python: >=3.11
Requires-Dist: mcp[cli]>=1.26.0
Requires-Dist: requests>=2.28.0
